adr_viewer/__init__.py
adr_viewer/test_adr_viewer.py
adr_viewer/templates/index.html
adr_viewer-1.1.1.dist-info/METADATA
adr_viewer-1.1.1.dist-info/RECORD
adr_viewer-1.1.1.dist-info/WHEEL
adr_viewer-1.1.1.dist-info/entry_points.txt
adr_viewer-1.1.1.dist-info/top_level.txt
