Metadata-Version: 2.1
Name: adr-viewer
Version: 1.1.1
Summary: A visualisation tool for Architecture Decision Records
Home-page: https://github.com/mrwilson/adr-viewer
Author: Alex Wilson
Author-email: a.wilson@alumni.warwick.ac.uk
License: MIT
Platform: UNKNOWN
Classifier: License :: OSI Approved :: MIT License
Classifier: Topic :: Software Development
Classifier: Topic :: Software Development :: Documentation
Classifier: Programming Language :: Python :: 2
Classifier: Programming Language :: Python :: 2.7
Classifier: Programming Language :: Python :: 3
Classifier: Programming Language :: Python :: 3.4
Classifier: Programming Language :: Python :: 3.5
Classifier: Programming Language :: Python :: 3.6
Requires-Dist: click
Requires-Dist: mistune
Requires-Dist: bs4
Requires-Dist: jinja2
Requires-Dist: bottle
